pisensors/__init__.py
pisensors/__main__.py
pisensors/config-template.yml
pisensors/sensors.py
pisensors-0.4.5.dist-info/METADATA
pisensors-0.4.5.dist-info/WHEEL
pisensors-0.4.5.dist-info/top_level.txt
pisensors-0.4.5.dist-info/RECORD
